<?xml version="1.0" encoding="utf-8" ?>
<dwsync>
<file name="SkyIsBlue-p-130x130q80.png" server="alt.spokenweb.ca" local="132911716250000000" remote="132911716250000000" Dst="2" />
<file name="webclip.jpg" server="alt.spokenweb.ca" local="132911716310000000" remote="132911716310000000" Dst="2" />
<file name="Web.svg" server="alt.spokenweb.ca" local="132911429480000000" remote="132911429480000000" Dst="2" />
<file name="ADP_logo-2_Solid.svg" server="alt.spokenweb.ca" local="132911716330000000" remote="132911716330000000" Dst="2" />
<file name="video-slash-solid.svg" server="alt.spokenweb.ca" local="132911716430000000" remote="132911716430000000" Dst="2" />
<file name="HomePage_Illustration_v2.gif" server="alt.spokenweb.ca" local="132911716230000000" remote="132911716230000000" Dst="2" />
<file name="web_yellow-01.svg" server="alt.spokenweb.ca" local="132911716230000000" remote="132911716230000000" Dst="2" />
<file name="ADP_logo2_256x256PX.ai" server="alt.spokenweb.ca" local="132911716250000000" remote="132911716250000000" Dst="2" />
<file name="Quote.svg" server="alt.spokenweb.ca" local="132911716450000000" remote="132911716450000000" Dst="2" />
<file name="book-open-solid.svg" server="alt.spokenweb.ca" local="132911429480000000" remote="132911429480000000" Dst="2" />
<file name="ADP_logo2_gradient.svg" server="alt.spokenweb.ca" local="132911716300000000" remote="132911716300000000" Dst="2" />
<file name="user-1-p-130x130q80.png" server="alt.spokenweb.ca" local="132911716430000000" remote="132911716430000000" Dst="2" />
<file name="Screen-Shot-2021-05-25-at-11.12.06-AM-p-500.png" server="alt.spokenweb.ca" local="132911716440000000" remote="132911716440000000" Dst="2" />
<file name="check-solid-white.svg" server="alt.spokenweb.ca" local="132911716450000000" remote="132911716450000000" Dst="2" />
<file name="ADP_logo2_Image.ai" server="alt.spokenweb.ca" local="132911716330000000" remote="132911716330000000" Dst="2" />
<file name="Instagram-1.svg" server="alt.spokenweb.ca" local="132911716450000000" remote="132911716450000000" Dst="2" />
<file name="search.png" server="alt.spokenweb.ca" local="132911716430000000" remote="132911716430000000" Dst="2" />
<file name="www_worldweb_orange.svg" server="alt.spokenweb.ca" local="132911716320000000" remote="132911716320000000" Dst="2" />
<file name="soundwave_transparent.psd" server="alt.spokenweb.ca" local="132911716360000000" remote="132911716360000000" Dst="2" />
<file name="HomePage_Illustration_v3-p-130x130q80.jpeg" server="alt.spokenweb.ca" local="132911716320000000" remote="132911716320000000" Dst="2" />
<file name="Lists_Illustration_v3.gif" server="alt.spokenweb.ca" local="132911716250000000" remote="132911716250000000" Dst="2" />
<file name="favicon.jpg" server="alt.spokenweb.ca" local="132911716280000000" remote="132911716280000000" Dst="2" />
<file name="SkyIsBlue.png" server="alt.spokenweb.ca" local="132911716430000000" remote="132911716430000000" Dst="2" />
<file name="Lists_Illustration_v2.gif" server="alt.spokenweb.ca" local="132911716250000000" remote="132911716250000000" Dst="2" />
<file name="Lists_Illustration_v2.psd" server="alt.spokenweb.ca" local="132911716350000000" remote="132911716350000000" Dst="2" />
<file name="plus2hours.svg" server="alt.spokenweb.ca" local="132911429480000000" remote="132911429480000000" Dst="2" />
<file name="bookmark-tag-p-130x130q80.png" server="alt.spokenweb.ca" local="132911716430000000" remote="132911716430000000" Dst="2" />
<file name="Data-icon-orange.svg" server="alt.spokenweb.ca" local="132911716310000000" remote="132911716310000000" Dst="2" />
<file name="Search.svg" server="alt.spokenweb.ca" local="132911716430000000" remote="132911716430000000" Dst="2" />
<file name="Image.svg" server="alt.spokenweb.ca" local="132911716440000000" remote="132911716440000000" Dst="2" />
<file name="Screen-Shot-2021-05-25-at-11.12.06-AM-p-800.png" server="alt.spokenweb.ca" local="132911716430000000" remote="132911716430000000" Dst="2" />
<file name="user-1.png" server="alt.spokenweb.ca" local="132911716450000000" remote="132911716450000000" Dst="2" />
<file name="Cancel-Icon-Orange.svg" server="alt.spokenweb.ca" local="132911716300000000" remote="132911716300000000" Dst="2" />
<file name="EvaCrocker_All_I_Ask-p-130x130q80.png" server="alt.spokenweb.ca" local="132911716280000000" remote="132911716280000000" Dst="2" />
<file name="no_video_solid_orange.svg" server="alt.spokenweb.ca" local="132911716240000000" remote="132911716240000000" Dst="2" />
<file name="comments-solid-01.svg" server="alt.spokenweb.ca" local="132911716320000000" remote="132911716320000000" Dst="2" />
<file name="HomePage_Illustration_v2.psd" server="alt.spokenweb.ca" local="132911716280000000" remote="132911716280000000" Dst="2" />
<file name="ADP_logo2_Image-01.jpg" server="alt.spokenweb.ca" local="132911716250000000" remote="132911716250000000" Dst="2" />
<file name="Facebook.svg" server="alt.spokenweb.ca" local="132911716450000000" remote="132911716450000000" Dst="2" />
<file name="1to2hours.svg" server="alt.spokenweb.ca" local="132911716310000000" remote="132911716310000000" Dst="2" />
<file name="star.svg" server="alt.spokenweb.ca" local="132911429480000000" remote="132911429480000000" Dst="2" />
<file name="comments-solid.svg" server="alt.spokenweb.ca" local="132911429480000000" remote="132911429480000000" Dst="2" />
<file name="components.svg" server="alt.spokenweb.ca" local="132911429480000000" remote="132911429480000000" Dst="2" />
<file name="ADP_logo2_256x256PX-01.jpg" server="alt.spokenweb.ca" local="132911716360000000" remote="132911716360000000" Dst="2" />
<file name="video-solid_orange.svg" server="alt.spokenweb.ca" local="132911716250000000" remote="132911716250000000" Dst="2" />
<file name="Cancel_icon_orange.svg" server="alt.spokenweb.ca" local="132911716230000000" remote="132911716230000000" Dst="2" />
<file name="file-export-solid.svg" server="alt.spokenweb.ca" local="132911716460000000" remote="132911716460000000" Dst="2" />
<file name="instagram_orange.svg" server="alt.spokenweb.ca" local="132911716240000000" remote="132911716240000000" Dst="2" />
<file name="event-p-130x130q80.png" server="alt.spokenweb.ca" local="132911716430000000" remote="132911716430000000" Dst="2" />
<file name="group-1-p-130x130q80.png" server="alt.spokenweb.ca" local="132911716430000000" remote="132911716430000000" Dst="2" />
<file name="Add.svg" server="alt.spokenweb.ca" local="132911429480000000" remote="132911429480000000" Dst="2" />
<file name="event.png" server="alt.spokenweb.ca" local="132911716430000000" remote="132911716430000000" Dst="2" />
<file name="HomePage_Illustration-01.psd" server="alt.spokenweb.ca" local="132911716310000000" remote="132911716310000000" Dst="2" />
<file name="conversation-solid-01.svg" server="alt.spokenweb.ca" local="132911716230000000" remote="132911716230000000" Dst="2" />
<file name="HomePage_Illustration.ai" server="alt.spokenweb.ca" local="132911716240000000" remote="132911716240000000" Dst="2" />
<file name="Facebook_orange.svg" server="alt.spokenweb.ca" local="132911716310000000" remote="132911716310000000" Dst="2" />
<file name="Union-5.svg" server="alt.spokenweb.ca" local="132911716430000000" remote="132911716430000000" Dst="2" />
<file name="Twitter.svg" server="alt.spokenweb.ca" local="132911716450000000" remote="132911716450000000" Dst="2" />
<file name="book-orange-solid.svg" server="alt.spokenweb.ca" local="132911716320000000" remote="132911716320000000" Dst="2" />
<file name="Twitter_orange.svg" server="alt.spokenweb.ca" local="132911716290000000" remote="132911716290000000" Dst="2" />
<file name="Add_icon_orange.svg" server="alt.spokenweb.ca" local="132911716330000000" remote="132911716330000000" Dst="2" />
<file name="Menu.svg" server="alt.spokenweb.ca" local="132911716460000000" remote="132911716460000000" Dst="2" />
<file name="filter-solid.svg" server="alt.spokenweb.ca" local="132911716440000000" remote="132911716440000000" Dst="2" />
<file name="EN_1.svg" server="alt.spokenweb.ca" local="132911716230000000" remote="132911716230000000" Dst="2" />
<file name="external-link-orange.svg" server="alt.spokenweb.ca" local="132911716330000000" remote="132911716330000000" Dst="2" />
<file name="webclip.png" server="alt.spokenweb.ca" local="132911429480000000" remote="132911429480000000" Dst="2" />
<file name="TreeReading_img.png" server="alt.spokenweb.ca" local="132911716450000000" remote="132911716450000000" Dst="2" />
<file name="Plus_orange.svg" server="alt.spokenweb.ca" local="132911716240000000" remote="132911716240000000" Dst="2" />
<file name="EN.svg" server="alt.spokenweb.ca" local="132911716430000000" remote="132911716430000000" Dst="2" />
<file name="web_click_orange.svg" server="alt.spokenweb.ca" local="132911716330000000" remote="132911716330000000" Dst="2" />
<file name="external-link-alt-solid.svg" server="alt.spokenweb.ca" local="132911716450000000" remote="132911716450000000" Dst="2" />
<file name="HomePage_Illustration-01.png" server="alt.spokenweb.ca" local="132911716290000000" remote="132911716290000000" Dst="2" />
<file name="Lists_Illustration_v3_1.gif" server="alt.spokenweb.ca" local="132911716360000000" remote="132911716360000000" Dst="2" />
<file name="play.svg" server="alt.spokenweb.ca" local="132911716440000000" remote="132911716440000000" Dst="2" />
<file name="favicon.ico" server="alt.spokenweb.ca" local="132911429480000000" remote="132911429480000000" Dst="2" />
<file name="FR.svg" server="alt.spokenweb.ca" local="132911716220000000" remote="132911716220000000" Dst="2" />
<file name="Screen-Shot-2021-05-25-at-11.12.06-AM-p-130x130q80.png" server="alt.spokenweb.ca" local="132911716450000000" remote="132911716450000000" Dst="2" />
<file name="Cancel.svg" server="alt.spokenweb.ca" local="132911429480000000" remote="132911429480000000" Dst="2" />
<file name="EvaCrocker_All_I_Ask.png" server="alt.spokenweb.ca" local="132911716430000000" remote="132911716430000000" Dst="2" />
<file name="group-1.png" server="alt.spokenweb.ca" local="132911716430000000" remote="132911716430000000" Dst="2" />
<file name="Lists_Illustration_v3.psd" server="alt.spokenweb.ca" local="132911716330000000" remote="132911716330000000" Dst="2" />
<file name="Lists_Illustration_v3_1-p-130x130q80.jpeg" server="alt.spokenweb.ca" local="132911716230000000" remote="132911716230000000" Dst="2" />
<file name="www_orange.svg" server="alt.spokenweb.ca" local="132911716310000000" remote="132911716310000000" Dst="2" />
<file name="HomePage_Illustration_v3.gif" server="alt.spokenweb.ca" local="132911716230000000" remote="132911716230000000" Dst="2" />
<file name="Genre-01.svg" server="alt.spokenweb.ca" local="132911716220000000" remote="132911716220000000" Dst="2" />
<file name="search-p-130x130q80.png" server="alt.spokenweb.ca" local="132911716430000000" remote="132911716430000000" Dst="2" />
<file name="ADP_logo2_32x32PX-01.jpg" server="alt.spokenweb.ca" local="132911716250000000" remote="132911716250000000" Dst="2" />
<file name="43---thumb.svg" server="alt.spokenweb.ca" local="132911716450000000" remote="132911716450000000" Dst="2" />
<file name="web_orange.svg" server="alt.spokenweb.ca" local="132911716360000000" remote="132911716360000000" Dst="2" />
<file name="copy-content-1.svg" server="alt.spokenweb.ca" local="132911429480000000" remote="132911429480000000" Dst="2" />
<file name="bookmark-tag.png" server="alt.spokenweb.ca" local="132911716450000000" remote="132911716450000000" Dst="2" />
<file name="HomePage_Illustration_v3.psd" server="alt.spokenweb.ca" local="132911716270000000" remote="132911716270000000" Dst="2" />
<file name="plus2hours-01.svg" server="alt.spokenweb.ca" local="132911716360000000" remote="132911716360000000" Dst="2" />
<file name="ADP_logo2_32x32PX.ai" server="alt.spokenweb.ca" local="132911716260000000" remote="132911716260000000" Dst="2" />
<file name="video-solid.svg" server="alt.spokenweb.ca" local="132911429480000000" remote="132911429480000000" Dst="2" />
<file name="VIAF_external-link-orange.svg" server="alt.spokenweb.ca" local="132911716310000000" remote="132911716310000000" Dst="2" />
<file name="Lists_Illustration_v3-p-130x130q80.jpeg" server="alt.spokenweb.ca" local="132911716230000000" remote="132911716230000000" Dst="2" />
<file name="Arrow-Down-Orange.svg" server="alt.spokenweb.ca" local="132911716230000000" remote="132911716230000000" Dst="2" />
</dwsync>